composio_lyzr/__init__.py
composio_lyzr/toolset.py
composio_lyzr-0.7.20.dist-info/METADATA
composio_lyzr-0.7.20.dist-info/WHEEL
composio_lyzr-0.7.20.dist-info/top_level.txt
composio_lyzr-0.7.20.dist-info/RECORD
