Metadata-Version: 2.4
Name: composio_lyzr
Version: 0.7.20
Summary: Use Composio to get an array of tools with your Lyzr workflow.
Home-page: https://github.com/ComposioHQ/composio
Author: Sawradip
Author-email: sawradip@composio.dev
Classifier: Programming Language :: Python :: 3
Classifier: License :: OSI Approved :: Apache Software License
Classifier: Operating System :: OS Independent
Requires-Python: >=3.9,<4
Requires-Dist: lyzr-automata>=0.1.3
Requires-Dist: pydantic>=2.6.4
Requires-Dist: composio_core<0.8.0,>=0.7.0
Requires-Dist: langchain>=0.1.0
Dynamic: author
Dynamic: author-email
Dynamic: classifier
Dynamic: description
Dynamic: description-content-type
Dynamic: home-page
Dynamic: requires-dist
Dynamic: requires-python
Dynamic: summary
